hunt/__init__.py
hunt/attributes/__init__.py
hunt/attributes/accolade.py
hunt/attributes/entry.py
hunt/attributes/match.py
hunt/attributes/parser.py
hunt/attributes/player.py
hunt/attributes/rewards.py
hunt/attributes/team.py
hunt/attributes/xml/__init__.py
hunt/attributes/xml/elements.py
hunt/attributes/xml/serializable.py
hunt/cli/__init__.py
hunt/cli/app.py
hunt/cli/arguments/__init__.py
hunt/cli/arguments/parser.py
hunt/cli/config.py
hunt/cli/exit_codes.py
hunt/constants.py
hunt/database/__init__.py
hunt/database/client.py
hunt/database/queries.py
hunt/exceptions.py
hunt/filesystem/__init__.py
hunt/filesystem/watchdog.py
hunt/formats.py
hunt/py.typed
hunt/reward_constants.py
hunt/steam/__init__.py
hunt/steam/api.py
hunt/steam/type_aliases.py
hunt_match_telemetry-1.7.2.dist-info/entry_points.txt
hunt_match_telemetry-1.7.2.dist-info/WHEEL
hunt_match_telemetry-1.7.2.dist-info/METADATA
hunt_match_telemetry-1.7.2.dist-info/RECORD
